azure/communication/rooms/__init__.py
azure/communication/rooms/_api_versions.py
azure/communication/rooms/_rooms_client.py
azure/communication/rooms/_version.py
azure/communication/rooms/py.typed
azure/communication/rooms/_generated/__init__.py
azure/communication/rooms/_generated/_client.py
azure/communication/rooms/_generated/_configuration.py
azure/communication/rooms/_generated/_patch.py
azure/communication/rooms/_generated/_serialization.py
azure/communication/rooms/_generated/_vendor.py
azure/communication/rooms/_generated/py.typed
azure/communication/rooms/_generated/aio/__init__.py
azure/communication/rooms/_generated/aio/_client.py
azure/communication/rooms/_generated/aio/_configuration.py
azure/communication/rooms/_generated/aio/_patch.py
azure/communication/rooms/_generated/aio/operations/__init__.py
azure/communication/rooms/_generated/aio/operations/_operations.py
azure/communication/rooms/_generated/aio/operations/_patch.py
azure/communication/rooms/_generated/operations/__init__.py
azure/communication/rooms/_generated/operations/_operations.py
azure/communication/rooms/_generated/operations/_patch.py
azure/communication/rooms/_models/__init__.py
azure/communication/rooms/_models/_models.py
azure/communication/rooms/_shared/__init__.py
azure/communication/rooms/_shared/auth_policy_utils.py
azure/communication/rooms/_shared/models.py
azure/communication/rooms/_shared/policy.py
azure/communication/rooms/_shared/user_credential.py
azure/communication/rooms/_shared/user_credential_async.py
azure/communication/rooms/_shared/utils.py
azure/communication/rooms/_shared/utils_async.py
azure/communication/rooms/aio/__init__.py
azure/communication/rooms/aio/_rooms_client_async.py
azure_communication_rooms-1.2.0.dist-info/LICENSE
azure_communication_rooms-1.2.0.dist-info/METADATA
azure_communication_rooms-1.2.0.dist-info/WHEEL
azure_communication_rooms-1.2.0.dist-info/top_level.txt
azure_communication_rooms-1.2.0.dist-info/RECORD
