Metadata-Version: 2.1
Name: azure-communication-rooms
Version: 1.2.0
Summary: Microsoft Communication Rooms Client Library for Python
Home-page: https://github.com/Azure/azure-sdk-for-python/tree/main/sdk/communication/azure-communication-rooms
Author: Microsoft Corporation
Author-email: azpysdkhelp@microsoft.com
License: MIT License
Keywords: azure,azure sdk
Classifier: Development Status :: 5 - Production/Stable
Classifier: Programming Language :: Python
Classifier: Programming Language :: Python :: 3 :: Only
Classifier: Programming Language :: Python :: 3
Classifier: Programming Language :: Python :: 3.8
Classifier: Programming Language :: Python :: 3.9
Classifier: Programming Language :: Python :: 3.10
Classifier: Programming Language :: Python :: 3.11
Classifier: Programming Language :: Python :: 3.12
Classifier: License :: OSI Approved :: MIT License
Requires-Python: >=3.8
License-File: LICENSE
Requires-Dist: azure-core >=1.32.0
Requires-Dist: isodate >=0.6.1
Requires-Dist: typing-extensions ; python_version<'3.8'
